{
  "chain": {
    "schemaVersion": 1,
    "chainKey": "wah",
    "chainName": "Westend Asset Hub",
    "genesisHash": "0x67f9723393ef76214df0118c34bbbd3dbebc8ed46a10973a8c969d48fe7598c9",
    "tokenSymbol": "WND",
    "tokenDecimals": 12,
    "ss58Prefix": 42
  },
  "era": 10693,
  "capturedAtMs": "1782080160000",
  "activeEraStartMs": "1782075396001",
  "eraDurationMs": "21600000",
  "sessionsPerEra": 6,
  "historyDepth": 84,
  "totalStakerReward": "129105367066446",
  "validatorIncentiveBudget": "91973292467685",
  "totalRewardPoints": 455460,
  "totalStake": "2649011969898791429",
  "sumIncentiveWeight": "3853718001",
  "incentiveParams": {
    "optimumSelfStake": "30000000000000000",
    "hardCapSelfStake": "100000000000000000",
    "selfStakeSlopeFactor": {
      "raw": 500000000,
      "fraction": 0.5
    }
  },
  "dapParams": {
    "budgetAllocation": {
      "buffer": {
        "raw": 226000000,
        "fraction": 0.226
      },
      "staker_rewards": {
        "raw": 452000000,
        "fraction": 0.452
      },
      "validator_incentive": {
        "raw": 322000000,
        "fraction": 0.322
      }
    },
    "issuanceCadenceMs": "60000",
    "maxElapsedPerDripMs": "600000",
    "lastIssuanceTimestampMs": "1782080136000"
  },
  "validators": [
    {
      "address": "5GTD7ZeD823BjpmZBCSzBQp7cvHR1Gunq7oDkurZr9zUev2n",
      "totalStake": "204607899073422506",
      "ownStake": "106394956087798246",
      "nominatorCount": 55,
      "pageCount": 1,
      "commission": {
        "raw": 1,
        "fraction": 1e-9
      },
      "blocked": false,
      "rewardPoints": 27960,
      "incentiveWeight": "217944947",
      "nominators": []
    },
    {
      "address": "5ENXqYmc5m6VLMm5i1mun832xAv2Qm9t3M4PWAFvvyCJLNoR",
      "totalStake": "174349807074978918",
      "ownStake": "79869261166961647",
      "nominatorCount": 79,
      "pageCount": 2,
      "commission": {
        "raw": 10000000,
        "fraction": 0.01
      },
      "blocked": false,
      "rewardPoints": 23460,
      "incentiveWeight": "206075993",
      "nominators": []
    },
    {
      "address": "5E2CYS4D6KdD1nDh5d7hTtss3TR8etx4i92ozipJt5QtR9KY",
      "totalStake": "157078285663545726",
      "ownStake": "64472732974358602",
      "nominatorCount": 61,
      "pageCount": 1,
      "commission": {
        "raw": 10000000,
        "fraction": 0.01
      },
      "blocked": false,
      "rewardPoints": 17360,
      "incentiveWeight": "196515096",
      "nominators": []
    },
    {
      "address": "5DJcEbkNxsnNwHGrseg7cgbfUG8eiKzpuZqgSph5HqHrjgf6",
      "totalStake": "151521002190193581",
      "ownStake": "64304086529067811",
      "nominatorCount": 56,
      "pageCount": 1,
      "commission": {
        "raw": 10000000,
        "fraction": 0.01
      },
      "blocked": false,
      "rewardPoints": 27500,
      "incentiveWeight": "196407794",
      "nominators": []
    },
    {
      "address": "5FUJHYEzKpVJfNbtXmR9HFqmcSEz6ak7ZUhBECz7GpsFkSYR",
      "totalStake": "134939403995348059",
      "ownStake": "43210838969695329",
      "nominatorCount": 105,
      "pageCount": 2,
      "commission": {
        "raw": 10000000,
        "fraction": 0.01
      },
      "blocked": false,
      "rewardPoints": 29000,
      "incentiveWeight": "182490300",
      "nominators": []
    },
    {
      "address": "5G1ojzh47Yt8KoYhuAjXpHcazvsoCXe3G8LZchKDvumozJJJ",
      "totalStake": "133530181431313686",
      "ownStake": "47434138284631779",
      "nominatorCount": 97,
      "pageCount": 2,
      "commission": {
        "raw": 220000000,
        "fraction": 0.22
      },
      "blocked": false,
      "rewardPoints": 16820,
      "incentiveWeight": "185360552",
      "nominators": []
    },
    {
      "address": "5H9ayWwwQoPFwFe7hcHussuro75SmRcQHacg9HEYb21oasMn",
      "totalStake": "128593050583972964",
      "ownStake": "128567514532333302",
      "nominatorCount": 4,
      "pageCount": 1,
      "commission": {
        "raw": 10000000,
        "fraction": 0.01
      },
      "blocked": false,
      "rewardPoints": 18700,
      "incentiveWeight": "217944947",
      "nominators": []
    },
    {
      "address": "5FNL7mJsaxfPeRku7eY93uMBw7xkaAbBX7c6ZNBdwGmReDQC",
      "totalStake": "128374946524933166",
      "ownStake": "128374867757949405",
      "nominatorCount": 1,
      "pageCount": 1,
      "commission": {
        "raw": 10000000,
        "fraction": 0.01
      },
      "blocked": false,
      "rewardPoints": 20660,
      "incentiveWeight": "217944947",
      "nominators": []
    },
    {
      "address": "5GYaYNVq6e855t5hVCyk4Wuqssaf6ADTrvdPZ3QXyHvFXTip",
      "totalStake": "128178620466248110",
      "ownStake": "42076559540574042",
      "nominatorCount": 138,
      "pageCount": 3,
      "commission": {
        "raw": 10000000,
        "fraction": 0.01
      },
      "blocked": false,
      "rewardPoints": 15980,
      "incentiveWeight": "181711694",
      "nominators": []
    },
    {
      "address": "5FnxSkypLBNFxc1XcjgvL6rHKCguMu4vTSee9Z5rJ5WVqdTX",
      "totalStake": "127792461528398835",
      "ownStake": "127752591681915454",
      "nominatorCount": 1,
      "pageCount": 1,
      "commission": {
        "raw": 10000000,
        "fraction": 0.01
      },
      "blocked": false,
      "rewardPoints": 23700,
      "incentiveWeight": "217944947",
      "nominators": []
    },
    {
      "address": "5F6UJyEWSdTcchyZpKTi7g5EiVWzwjVcnwcZjv1mmN3AXN2T",
      "totalStake": "127357887173265214",
      "ownStake": "127332572482369264",
      "nominatorCount": 2,
      "pageCount": 1,
      "commission": {
        "raw": 10000000,
        "fraction": 0.01
      },
      "blocked": false,
      "rewardPoints": 24420,
      "incentiveWeight": "217944947",
      "nominators": []
    },
    {
      "address": "5FWG1xiaSSxR4kCTFo3nVGdz3T2fkajUfEtj4qEFHwnq4iVx",
      "totalStake": "127334274386199149",
      "ownStake": "127334081962158283",
      "nominatorCount": 1,
      "pageCount": 1,
      "commission": {
        "raw": 10000000,
        "fraction": 0.01
      },
      "blocked": false,
      "rewardPoints": 21060,
      "incentiveWeight": "217944947",
      "nominators": []
    },
    {
      "address": "5Ft3J6iqSQPWX2S9jERXcMpevt8JDUPWjec5uGierfVGXisE",
      "totalStake": "125680875769113920",
      "ownStake": "43374560239177570",
      "nominatorCount": 77,
      "pageCount": 2,
      "commission": {
        "raw": 10000000,
        "fraction": 0.01
      },
      "blocked": false,
      "rewardPoints": 24560,
      "incentiveWeight": "182602409",
      "nominators": []
    },
    {
      "address": "5CFPqoTU7fiUp1JJNbfcY2z6yavEBKDPQGg4SGeG3Fm7vCsg",
      "totalStake": "122097804747649251",
      "ownStake": "41784224366243136",
      "nominatorCount": 71,
      "pageCount": 2,
      "commission": {
        "raw": 10000000,
        "fraction": 0.01
      },
      "blocked": false,
      "rewardPoints": 20200,
      "incentiveWeight": "181510484",
      "nominators": []
    },
    {
      "address": "5HYYWyhyUQ7Ae11f8fCid58bhJ7ikLHM9bU8A6Ynwoc3dStR",
      "totalStake": "119192433459509960",
      "ownStake": "40685011208332904",
      "nominatorCount": 69,
      "pageCount": 2,
      "commission": {
        "raw": 120000000,
        "fraction": 0.12
      },
      "blocked": false,
      "rewardPoints": 14900,
      "incentiveWeight": "180751909",
      "nominators": []
    },
    {
      "address": "5FEjMPSs4X2XNes7QRH6eLmaYCskHdnYM8Zv2kKrBrhnzGbR",
      "totalStake": "116668500524176490",
      "ownStake": "40649360339144386",
      "nominatorCount": 79,
      "pageCount": 2,
      "commission": {
        "raw": 10000000,
        "fraction": 0.01
      },
      "blocked": false,
      "rewardPoints": 22760,
      "incentiveWeight": "180727253",
      "nominators": []
    },
    {
      "address": "5C556QTtg1bJ43GDSgeowa3Ark6aeSHGTac1b2rKSXtgmSmW",
      "totalStake": "114410001935660497",
      "ownStake": "40923561253625961",
      "nominatorCount": 70,
      "pageCount": 2,
      "commission": {
        "raw": 10000000,
        "fraction": 0.01
      },
      "blocked": false,
      "rewardPoints": 23660,
      "incentiveWeight": "180916804",
      "nominators": []
    },
    {
      "address": "5FZoQhgUCmqBxnkHX7jCqThScS2xQWiwiF61msg63CFL3Y8f",
      "totalStake": "111269302524733826",
      "ownStake": "30610542957703873",
      "nominatorCount": 85,
      "pageCount": 2,
      "commission": {
        "raw": 1,
        "fraction": 1e-9
      },
      "blocked": false,
      "rewardPoints": 28760,
      "incentiveWeight": "173645143",
      "nominators": []
    },
    {
      "address": "5CFPcUJgYgWryPaV1aYjSbTpbTLu42V32Ytw1L9rfoMAsfGh",
      "totalStake": "109378400566846442",
      "ownStake": "29557953530235517",
      "nominatorCount": 141,
      "pageCount": 3,
      "commission": {
        "raw": 1,
        "fraction": 1e-9
      },
      "blocked": false,
      "rewardPoints": 29740,
      "incentiveWeight": "171924266",
      "nominators": []
    },
    {
      "address": "5Ek5JCnrRsyUGYNRaEvkufG1i1EUxEE9cytuWBBjA9oNZVsf",
      "totalStake": "106656830279281129",
      "ownStake": "21143667398761734",
      "nominatorCount": 93,
      "pageCount": 2,
      "commission": {
        "raw": 10000000,
        "fraction": 0.01
      },
      "blocked": false,
      "rewardPoints": 24260,
      "incentiveWeight": "145408622",
      "nominators": []
    }
  ]
}
